ajm_discord/__init__.py
ajm_discord/ajm_discord.py
ajm_discord-1.0.2.7.dist-info/LICENSE.md
ajm_discord-1.0.2.7.dist-info/METADATA
ajm_discord-1.0.2.7.dist-info/WHEEL
ajm_discord-1.0.2.7.dist-info/top_level.txt
ajm_discord-1.0.2.7.dist-info/RECORD
