Metadata-Version: 2.1
Name: ajm-discord
Version: 1.0.2.7
Summary: Some useful discord cog/bots.
Home-page: https://github.com/challos/ajm_discord
Author: Andrew McGrail
Author-email: andrewjerrismcgrail@gmail.com
License: MIT License (MIT)
License-File: LICENSE.md
Requires-Dist: py-cord (>=2.0.0rc1)
Requires-Dist: python-docx
